bref_scraper/__init__.py
bref_scraper/constants.py
bref_scraper/players.py
bref_scraper/teams.py
bref_scraper/utils/__init__.py
bref_scraper/utils/html_helpers.py
bref_scraper-0.1.0.dist-info/licenses/LICENSE
bref_scraper-0.1.0.dist-info/METADATA
bref_scraper-0.1.0.dist-info/WHEEL
bref_scraper-0.1.0.dist-info/top_level.txt
bref_scraper-0.1.0.dist-info/RECORD
