Metadata-Version: 2.4
Name: bref-scraper
Version: 0.1.0
Summary: A Python scraper for stats and box scores from Basketball Reference
Author-email: Jithen Shriyan <shriyanjithen@gmail.com>
License: MIT
Project-URL: Homepage, https://github.com/jithenms/bref_scraper
Project-URL: Repository, https://github.com/jithenms/bref_scraper
Project-URL: Issues, https://github.com/jithenms/bref_scraper/issues
Keywords: nba,basketball,sports,web scraping,beautifulsoup,stats,basketball-reference,player stats,python,scraper
Requires-Python: >=3.8
License-File: LICENSE
Requires-Dist: requests
Requires-Dist: beautifulsoup4
Dynamic: license-file
